---
title: JVM Class 文件格式与字节码指令集精讲：从魔数到助记符
date: 2026-07-20 08:00:00
tags:
  - JVM
  - 字节码
  - 原理
  - Class文件
categories:
  - JVM
  - 字节码与原理
author: 东哥
---

# JVM Class 文件格式与字节码指令集精讲：从魔数到助记符

## 一、为什么需要理解 Class 文件？

"Java 是跨平台的语言，而 JVM 是跨语言的平台。"

`.class` 文件是 JVM 的"机器码"，理解它的结构不仅能帮你深入理解 JVM 的工作机制，还在以下场景中非常有用：

- **JVM 调优**：理解字节码层面如何优化
- **字节码增强**：Spring AOP、MyBatis、Lombok、热部署等技术的底层基础
- **反编译与安全**：分析混淆代码、理解 APM 原理
- **面试高频题**：大厂面试中 Class 文件结构几乎是必问项

## 二、Class 文件结构概览

每个 `.class` 文件对应一个类（或接口）的定义，采用 **大端序（Big-Endian）** 存储，包含以下固定结构：

```c
ClassFile {
    u4             magic;               // 魔数：0xCAFEBABE
    u2             minor_version;       // 次版本号
    u2             major_version;       // 主版本号
    u2             constant_pool_count; // 常量池计数
    cp_info        constant_pool[constant_pool_count-1]; // 常量池
    u2             access_flags;        // 访问标志
    u2             this_class;          // 当前类索引
    u2             super_class;         // 父类索引
    u2             interfaces_count;    // 接口计数
    u2             interfaces[interfaces_count]; // 接口索引集合
    u2             fields_count;        // 字段计数
    field_info     fields[fields_count]; // 字段表
    u2             methods_count;       // 方法计数
    method_info    methods[methods_count]; // 方法表
    u2             attributes_count;    // 属性计数
    attribute_info attributes[attributes_count]; // 属性表
}
```

### 2.1 魔数

所有 `.class` 文件的前 4 个字节固定为 `0xCAFEBABE`（咖啡宝贝），这是 JVM 识别 Class 文件的标志，类似于文件系统的"魔数签名"。

> **冷知识**：Java 的创始人们喜欢咖啡，所以用了 `0xCAFEBABE` 作为魔数。James Gosling 在一次访谈中提到这是在某个咖啡馆里想到的。

### 2.2 版本号

| 字节 | 含义 | 示例 |
|---|---|---|
| `minor_version` | 次版本号 | `0x0000` |
| `major_version` | 主版本号 | `0x003C` → JDK 8（60），`0x0040` → JDK 16（64） |

各 JDK 版本对应的主版本号：

| JDK 版本 | 主版本号（十进制） | 十六进制 |
|---|---|---|
| JDK 8 | 52 | `0x0034` |
| JDK 11 | 55 | `0x0037` |
| JDK 17 | 61 | `0x003D` |
| JDK 21 | 65 | `0x0041` |
| JDK 24 | 68 | `0x0044` |

## 三、常量池（Constant Pool）—— Class 文件的"资源仓库"

常量池是 Class 文件中最核心、最复杂的部分，它存储了类中用到的所有字面量和符号引用。

### 3.1 常量池项类型

常量池中一共有 **17 种常量类型**（JDK 8 后有所增加）：

| 类型 | 标志 | 描述 |
|---|---|---|
| `CONSTANT_Utf8` | 1 | UTF-8 编码的字符串 |
| `CONSTANT_Integer` | 3 | int 型字面量 |
| `CONSTANT_Float` | 4 | float 型字面量 |
| `CONSTANT_Long` | 5 | long 型字面量 |
| `CONSTANT_Double` | 6 | double 型字面量 |
| `CONSTANT_Class` | 7 | 类或接口的符号引用 |
| `CONSTANT_String` | 8 | String 类型字面量 |
| `CONSTANT_Fieldref` | 9 | 字段符号引用 |
| `CONSTANT_Methodref` | 10 | 方法符号引用 |
| `CONSTANT_InterfaceMethodref` | 11 | 接口方法符号引用 |
| `CONSTANT_NameAndType` | 12 | 字段或方法的名称和类型描述符 |
| `CONSTANT_MethodHandle` | 15 | 方法句柄 |
| `CONSTANT_MethodType` | 16 | 方法类型 |
| `CONSTANT_InvokeDynamic` | 18 | 动态调用点 |
| `CONSTANT_Module` | 19 | 模块信息（Java 9+） |
| `CONSTANT_Package` | 20 | 包信息（Java 9+） |

### 3.2 验证常量池

通过 `javap -verbose` 命令查看 Class 文件常量池：

```java
// 示例类
public class Hello {
    private String name = "东哥";
    
    public void sayHello() {
        System.out.println("Hello, " + name);
    }
}
```

编译后执行 `javap -verbose Hello.class`，你会看到几百行输出，其中常量池部分：

```
Constant pool:
   #1 = Methodref    #2.#3      // java/lang/Object."<init>":()V
   #2 = Class        #4         // java/lang/Object
   #3 = NameAndType  #5:#6      // "<init>":()V
   #4 = Utf8         java/lang/Object
   #5 = Utf8         <init>
   #6 = Utf8         ()V
   #7 = Fieldref     #8.#9      // Hello.name:Ljava/lang/String;
   #8 = Class        #10        // Hello
   #9 = NameAndType  #11:#12    // name:Ljava/lang/String;
  #10 = Utf8         Hello
  #11 = Utf8         name
  #12 = Utf8         Ljava/lang/String;
  #13 = String       #14        // 东哥
  #14 = Utf8         东哥
  #15 = Fieldref     #16.#17    // java/lang/System.out:Ljava/io/PrintStream;
  #16 = Class        #18        // java/lang/System
  #17 = NameAndType  #19:#20    // out:Ljava/io/PrintStream;
  #18 = Utf8         java/lang/System
  #19 = Utf8         out
  #20 = Utf8         Ljava/io/PrintStream;
  ...
```

可以看到，**所有字符串常量、类名、方法名、字段名都以 CONSTANT_Utf8 形式存储在常量池中**，其他地方只通过索引引用。

## 四、访问标志与类索引

### 4.1 access_flags（访问标志）

2 个字节，表示类或接口的访问权限和属性：

| 标志名 | 值 | 含义 |
|---|---|---|
| `ACC_PUBLIC` | `0x0001` | public 类型 |
| `ACC_FINAL` | `0x0010` | final 类，不允许继承 |
| `ACC_SUPER` | `0x0020` | 使用 invokespecial 指令的语义（JDK 1.2 后默认设置） |
| `ACC_INTERFACE` | `0x0200` | 是接口 |
| `ACC_ABSTRACT` | `0x0400` | 抽象类 |
| `ACC_ANNOTATION` | `0x2000` | 注解类型 |
| `ACC_ENUM` | `0x4000` | 枚举类型 |
| `ACC_MODULE` | `0x8000` | 模块（Java 9+） |

例如 `public class Hello` 的标志是 `ACC_PUBLIC | ACC_SUPER = 0x0021`。

## 五、字段表和方法表

### 5.1 field_info（字段表）

```c
field_info {
    u2             access_flags;   // 访问标志
    u2             name_index;     // 字段名在常量池的索引
    u2             descriptor_index; // 描述符索引
    u2             attributes_count;
    attribute_info attributes[attributes_count];
}
```

**字段描述符**：

| 描述符 | 含义 |
|---|---|
| `B` | byte |
| `C` | char |
| `D` | double |
| `F` | float |
| `I` | int |
| `J` | long |
| `S` | short |
| `Z` | boolean |
| `V` | void |
| `LClassName;` | 引用类型，如 `Ljava/lang/String;` |
| `[` | 数组，如 `[I` 表示 int[] |

### 5.2 method_info（方法表）

```c
method_info {
    u2             access_flags;
    u2             name_index;
    u2             descriptor_index;
    u2             attributes_count;
    attribute_info attributes[attributes_count];
}
```

**方法描述符格式**：`(参数类型)返回值类型`

| 方法签名 | 描述符 |
|---|---|
| `void run()` | `()V` |
| `int add(int a, int b)` | `(II)I` |
| `String getName(int id)` | `(I)Ljava/lang/String;` |
| `void setData(String[] arr)` | `([Ljava/lang/String;)V` |

## 六、属性表（Attribute）——最丰富的扩展机制

属性表是 Class 文件中 **最灵活、最核心** 的部分，字段、方法和 Class 本身都可以携带属性。常见属性：

| 属性名称 | 所属 | 用途 |
|---|---|---|
| `Code` | 方法 | 存储方法的字节码指令 |
| `LineNumberTable` | `Code` | 源码行号与字节码偏移映射 |
| `LocalVariableTable` | `Code` | 局部变量描述 |
| `StackMapTable` | `Code` | 类型检查验证（JDK 6+） |
| `Exceptions` | 方法 | 方法抛出的异常列表 |
| `ConstantValue` | 字段 | final 常量值 |
| `Synthetic` | 类/方法/字段 | 标记编译器生成的代码 |
| `InnerClasses` | 类 | 内部类列表 |
| `Signature` | 类/方法/字段 | 泛型签名 |
| `Annotations` | 类/方法/字段 | 运行时可见注解 |
| `BootstrapMethods` | 类 | Lambda 表达式引导方法 |
| `NestHost` / `NestMembers` | 类 | 嵌套类（Java 11+） |
| `Record` | 类 | Record 类（Java 16+） |

## 七、字节码指令集精讲

### 7.1 指令分类

JVM 字节码指令共有 **256 条**（其中约 200 多条常用），按功能分为以下几类：

| 类别 | 说明 | 典型指令 |
|---|---|---|
| 加载和存储 | 在局部变量表和操作数栈间传数据 | `iload`、`istore`、`aload`、`astore`、`ldc` |
| 算术运算 | 数值计算 | `iadd`、`isub`、`imul`、`idiv` |
| 类型转换 | 类型互相转换 | `i2l`、`d2f`、`checkcast`、`instanceof` |
| 对象创建操作 | 创建对象和数组 | `new`、`newarray`、`multianewarray` |
| 操作数栈管理 | 栈操作 | `pop`、`dup`、`swap` |
| 控制转移 | 条件判断和跳转 | `ifeq`、`goto`、`tableswitch`、`lookupswitch` |
| 方法调用和返回 | 调用和返回 | `invokevirtual`、`invokespecial`、`invokestatic`、`invokeinterface`、`invokedynamic` |
| 异常处理 | 抛出异常 | `athrow` |
| 同步 | 锁操作 | `monitorenter`、`monitorexit` |

### 7.2 方法调用指令详解

这是面试中 **最常考** 的知识点：

| 指令 | 用途 | 例子 |
|---|---|---|
| `invokevirtual` | 调用实例方法（虚方法分派） | `obj.toString()` |
| `invokespecial` | 调用构造器、私有方法、父类方法 | `<init>`、`super.method()` |
| `invokestatic` | 调用静态方法 | `Math.max(a, b)` |
| `invokeinterface` | 调用接口方法 | `list.add(item)` |
| `invokedynamic` | 动态调用（Java 7+，Lambda 表达式的底层） | `list.forEach(x -> ...)` |

### 7.3 实战：字节码反汇编

来看一段简单 Java 代码的反汇编结果：

```java
public int add(int a, int b) {
    return a + b;
}
```

执行 `javap -c` 得到：

```
public int add(int, int);
  Code:
     0: iload_1          // 将局部变量表 index=1 的 int 值压栈 (a)
     1: iload_2          // 将局部变量表 index=2 的 int 值压栈 (b)
     2: iadd             // 弹出栈顶两个 int，相加后将结果压栈
     3: ireturn          // 返回栈顶 int 值
```

再来看一个带条件判断的：

```java
public String checkScore(int score) {
    if (score >= 60) {
        return "及格";
    }
    return "不及格";
}
```

反汇编：

```
 0: iload_1               // 加载 score
 1: bipush        60       // 将常量 60 压栈
 3: if_icmplt     12       // 如果 score < 60，跳转到 12
 6: ldc           #7       // 从常量池加载"及格"
 8: areturn                 // 返回引用
 9: ldc           #9       // 从常量池加载"不及格"
11: areturn
12: ldc           #9       // 从常量池加载"不及格"
14: areturn
```

可以看到编译器做了 **少许优化**（两条路径加载同一个字符串），但不是完全消除冗余。如果进一步用 `-O` 优化或使用 JIT，最终机器码会更高效。

## 八、Lambda 表达式的字节码：invokedynamic

Java 8 引入的 Lambda 表达式底层使用 `invokedynamic` 指令和 `BootstrapMethods` 属性：

```java
// 源码
list.forEach(item -> System.out.println(item));
```

对应的字节码：

```
invokedynamic #7,  0  // InvokeDynamic #0:accept:()Ljava/util/function/Consumer;
```

```java
// BootstrapMethods 属性
BootstrapMethods:
  0: #56 invokestatic java/lang/invoke/LambdaMetafactory.metafactory:...
    Method arguments:
      #57 (Ljava/lang/Object;)V
      #58 invokestatic com/example/Main.lambda$main$0:(Ljava/lang/String;)V
      #59 (Ljava/lang/String;)V
```

**为什么用 invokedynamic？**

- **延迟生成**：Lambda 对应的匿名内部类在运行时才通过 `LambdaMetafactory` 生成
- **性能优化**：如果 Lambda 不捕获外部变量，生成的内部类是单例的，避免重复创建
- **策略自由**：JVM 实现可以选择内联、缓存等多种优化策略

## 九、常见面试题

### Q1：Class 文件的魔数是什么？有什么作用？

魔数是 `0xCAFEBABE`，作用是让 JVM 快速识别一个文件是否为合法的 Class 文件，类似于文件系统的魔数签名。

### Q2：符号引用和直接引用的区别？

- **符号引用**：在 Class 文件中以 CONSTANT_* 形式存放的字符串常量（如 `java/lang/Object`），不依赖于具体内存地址
- **直接引用**：类加载的解析阶段，将符号引用替换为实际的内存地址（方法区指针、偏移量等）

### Q3：invokevirtual 和 invokespecial 的区别？

`invokevirtual` 支持多态（虚方法分派），运行时根据对象实际类型选择调用版本；`invokespecial` 在编译期就确定了目标方法，用于构造器、私有方法和父类方法。

### Q4：Lambda 表达式在字节码层面是如何实现的？

通过 `invokedynamic` + `BootstrapMethods`，运行时由 `LambdaMetafactory` 生成内部类实例。如果 Lambda 不捕获外部变量，生成的匿名内部类是单例的。

## 十、总结

| 结构 | 说明 | 关键点 |
|---|---|---|
| 魔数 | `0xCAFEBABE` | 文件格式标识 |
| 常量池 | 存储字面量和符号引用 | 最常见、最复杂的部分 |
| 访问标志 | 类/方法/字段的访问控制 | `ACC_PUBLIC`、`ACC_FINAL` 等 |
| 字段表 | 字段定义 | 描述符指定类型 |
| 方法表 | 方法定义 | Code 属性存储字节码 |
| 属性表 | 扩展信息 | Code、LineNumberTable 等 |
| 字节码指令 | JVM 执行的指令 | 256 条指令，200+ 常用 |

理解 Class 文件结构和字节码指令，是从"会用 Java"到"懂 Java"的关键一步。它不仅支撑着 Spring AOP、Lombok、热部署等技术，也是深入 JVM 底层原理的必经之路。
